cascade/__init__.py
cascade/celestra_extensions.py
cascade/llm_wrappers.py
cascade/tool_decorator.py
cascade/tracing.py
cascade/utils.py
cascade/cli/__init__.py
cascade/cli/main.py
cascade/cli/start.py
cascade/cli/status.py
cascade/cli/stop.py
cascade/cli/utils.py
cascade/exporters/__init__.py
cascade/exporters/json_exporter.py
cascade_sdk-0.2.0b9.dist-info/METADATA
cascade_sdk-0.2.0b9.dist-info/WHEEL
cascade_sdk-0.2.0b9.dist-info/entry_points.txt
cascade_sdk-0.2.0b9.dist-info/top_level.txt
cascade_sdk-0.2.0b9.dist-info/RECORD
