Metadata-Version: 2.4
Name: cascade-sdk
Version: 0.2.0b9
Summary: Agent observability SDK for tracking AI agent execution
Author: Cascade
Requires-Python: >=3.8
Requires-Dist: opentelemetry-api>=1.20.0
Requires-Dist: opentelemetry-sdk>=1.20.0
Requires-Dist: opentelemetry-exporter-otlp>=1.20.0
Requires-Dist: click>=8.0.0
Dynamic: author
Dynamic: requires-python
